Workbook

Sheet Dashboard
B2: Developer Job Application Tracker PRO
B3: Executive Dashboard · v3.0 · CreatorDockStudio
B6: Total Applications | D6: Active Applications | F6: Interviews | H6: Offers
B7: =COUNTA(Applications!B2:B500) | D7: =COUNTIFS(Applications!J2:J500,"<>Rejected",Applications!J2:J500,"<>Ghosted",Applications!J2:J500,"<>Withdrawn",Applications!J2:J500,"<>Accepted",Applications!B2:B500,"<>") | F7: =COUNTIFS(Applications!J2:J500,"*Interview*",Applications!B2:B500,"<>") | H7: =COUNTIFS(Applications!J2:J500,"Offer",Applications!B2:B500,"<>")+COUNTIFS(Applications!J2:J500,"Accepted",Applications!B2:B500,"<>")
B9: Technical Interviews | D9: HR Interviews | F9: Final Interviews | H9: Accepted Offers
B10: =COUNTIFS(Applications!J2:J500,"Technical Interview",Applications!B2:B500,"<>") | D10: =COUNTIFS(Applications!J2:J500,"HR Interview",Applications!B2:B500,"<>") | F10: =COUNTIFS(Applications!J2:J500,"Final Interview",Applications!B2:B500,"<>") | H10: =COUNTIFS(Applications!J2:J500,"Accepted",Applications!B2:B500,"<>")
B12: Rejections | D12: Ghosted | F12: Pending Responses | H12: Response Rate
B13: =COUNTIFS(Applications!J2:J500,"Rejected",Applications!B2:B500,"<>") | D13: =COUNTIFS(Applications!J2:J500,"Ghosted",Applications!B2:B500,"<>") | F13: =COUNTIFS(Applications!J2:J500,"Applied",Applications!B2:B500,"<>")+COUNTIFS(Applications!J2:J500,"Screening",Applications!B2:B500,"<>") | H13: =IFERROR(ROUND((COUNTIFS(Applications!J2:J500,"<>Applied",Applications!J2:J500,"<>",Applications!B2:B500,"<>")-COUNTIFS(Applications!J2:J500,"Ghosted",Applications!B2:B500,"<>"))/COUNTA(Applications!B2:B500),2),0)
B15: Performance Metrics
B16: Interview Rate | D16: Offer Rate | F16: Success Rate
B17: =IFERROR(ROUND(COUNTIFS(Applications!J2:J500,"*Interview*",Applications!B2:B500,"<>")/COUNTA(Applications!B2:B500),2),0) | D17: =IFERROR(ROUND((COUNTIFS(Applications!J2:J500,"Offer",Applications!B2:B500,"<>")+COUNTIFS(Applications!J2:J500,"Accepted",Applications!B2:B500,"<>"))/COUNTA(Applications!B2:B500),2),0) | F17: =IFERROR(ROUND(COUNTIFS(Applications!J2:J500,"Accepted",Applications!B2:B500,"<>")/COUNTA(Applications!B2:B500),2),0)
B19: Avg Fit Score | D19: Avg Decision Score | F19: Ghost Rate
B20: =IFERROR(ROUND(AVERAGEIF(Applications!L2:L500,">0"),0),0) | D20: =IFERROR(ROUND(AVERAGE('Offer Decision Matrix'!R2:R500),1),0) | F20: =IFERROR(ROUND(COUNTIFS(Applications!J2:J500,"Ghosted",Applications!B2:B500,"<>")/COUNTA(Applications!B2:B500),2),0)
B22: Goal Progress
B23: Monthly Goal | D23: Weekly Goal | F23: Interviews Goal | H23: Networking Goal
B24: =COUNTIFS(Applications!I2:I500,">="&EOMONTH(TODAY(),-1)+1,Applications!I2:I500,"<="&EOMONTH(TODAY(),0)) | C24: ="/ "&50 | D24: =COUNTIFS(Applications!I2:I500,">="&TODAY()-WEEKDAY(TODAY())+1,Applications!I2:I500,"<="&TODAY()-WEEKDAY(TODAY())+7) | E24: ="/ "&10 | F24: =COUNTIFS(Applications!J2:J500,"*Interview*",Applications!I2:I500,">="&EOMONTH(TODAY(),-1)+1) | G24: ="/ "&5 | H24: =COUNTA('Networking Tracker'!A2:A500) | I24: ="/ "&20
B30: Status | C30: Count | E30: Source | F30: Count
B31: Applied | C31: =COUNTIFS(Applications!J2:J500,"Applied",Applications!B2:B500,"<>") | E31: LinkedIn | F31: =COUNTIFS(Applications!H2:H500,"LinkedIn",Applications!B2:B500,"<>")
B32: Screening | C32: =COUNTIFS(Applications!J2:J500,"Screening",Applications!B2:B500,"<>") | E32: Indeed | F32: =COUNTIFS(Applications!H2:H500,"Indeed",Applications!B2:B500,"<>")
B33: Phone Screen | C33: =COUNTIFS(Applications!J2:J500,"Phone Screen",Applications!B2:B500,"<>") | E33: AngelList | F33: =COUNTIFS(Applications!H2:H500,"AngelList",Applications!B2:B500,"<>")
B34: Technical Interview | C34: =COUNTIFS(Applications!J2:J500,"Technical Interview",Applications!B2:B500,"<>") | E34: Glassdoor | F34: =COUNTIFS(Applications!H2:H500,"Glassdoor",Applications!B2:B500,"<>")
B35: HR Interview | C35: =COUNTIFS(Applications!J2:J500,"HR Interview",Applications!B2:B500,"<>") | E35: Company Website | F35: =COUNTIFS(Applications!H2:H500,"Company Website",Applications!B2:B500,"<>")
B36: Final Interview | C36: =COUNTIFS(Applications!J2:J500,"Final Interview",Applications!B2:B500,"<>") | E36: Referral | F36: =COUNTIFS(Applications!H2:H500,"Referral",Applications!B2:B500,"<>")
B37: Offer | C37: =COUNTIFS(Applications!J2:J500,"Offer",Applications!B2:B500,"<>") | E37: Recruiter | F37: =COUNTIFS(Applications!H2:H500,"Recruiter",Applications!B2:B500,"<>")
B38: Accepted | C38: =COUNTIFS(Applications!J2:J500,"Accepted",Applications!B2:B500,"<>") | E38: Job Fair | F38: =COUNTIFS(Applications!H2:H500,"Job Fair",Applications!B2:B500,"<>")
B39: Rejected | C39: =COUNTIFS(Applications!J2:J500,"Rejected",Applications!B2:B500,"<>") | E39: Other | F39: =COUNTIFS(Applications!H2:H500,"Other",Applications!B2:B500,"<>")
B40: Ghosted | C40: =COUNTIFS(Applications!J2:J500,"Ghosted",Applications!B2:B500,"<>")
B41: Withdrawn | C41: =COUNTIFS(Applications!J2:J500,"Withdrawn",Applications!B2:B500,"<>")
B45: Work Type | C45: Count | E45: Priority | F45: Count
B46: Remote | C46: =COUNTIFS(Applications!F2:F500,"Remote",Applications!B2:B500,"<>") | E46: Critical | F46: =COUNTIFS(Applications!K2:K500,"Critical",Applications!B2:B500,"<>")
B47: Hybrid | C47: =COUNTIFS(Applications!F2:F500,"Hybrid",Applications!B2:B500,"<>") | E47: High | F47: =COUNTIFS(Applications!K2:K500,"High",Applications!B2:B500,"<>")
B48: Onsite | C48: =COUNTIFS(Applications!F2:F500,"Onsite",Applications!B2:B500,"<>") | E48: Medium | F48: =COUNTIFS(Applications!K2:K500,"Medium",Applications!B2:B500,"<>")
B49: Flexible | C49: =COUNTIFS(Applications!F2:F500,"Flexible",Applications!B2:B500,"<>") | E49: Low | F49: =COUNTIFS(Applications!K2:K500,"Low",Applications!B2:B500,"<>")
B52: Month | C52: Count | E52: Funnel Stage | F52: Count
B53: =TEXT(EOMONTH(TODAY(),-5),"MMM YYYY") | C53: =COUNTIFS(Applications!I2:I500,">="&EOMONTH(TODAY(),-5-1)+1,Applications!I2:I500,"<="&EOMONTH(TODAY(),-5)) | E53: Applied | F53: =COUNTA(Applications!B2:B500)
B54: =TEXT(EOMONTH(TODAY(),-4),"MMM YYYY") | C54: =COUNTIFS(Applications!I2:I500,">="&EOMONTH(TODAY(),-4-1)+1,Applications!I2:I500,"<="&EOMONTH(TODAY(),-4)) | E54: Screening | F54: =COUNTIFS(Applications!J2:J500,"Screening",Applications!B2:B500,"<>")+COUNTIFS(Applications!J2:J500,"Phone Screen",Applications!B2:B500,"<>")+COUNTIFS(Applications!J2:J500,"*Interview*",Applications!B2:B500,"<>")+COUNTIFS(Applications!J2:J500,"Offer",Applications!B2:B500,"<>")+COUNTIFS(Applications!J2:J500,"Accepted",Applications!B2:B500,"<>")
B55: =TEXT(EOMONTH(TODAY(),-3),"MMM YYYY") | C55: =COUNTIFS(Applications!I2:I500,">="&EOMONTH(TODAY(),-3-1)+1,Applications!I2:I500,"<="&EOMONTH(TODAY(),-3)) | E55: Interview | F55: =COUNTIFS(Applications!J2:J500,"*Interview*",Applications!B2:B500,"<>")+COUNTIFS(Applications!J2:J500,"Offer",Applications!B2:B500,"<>")+COUNTIFS(Applications!J2:J500,"Accepted",Applications!B2:B500,"<>")
B56: =TEXT(EOMONTH(TODAY(),-2),"MMM YYYY") | C56: =COUNTIFS(Applications!I2:I500,">="&EOMONTH(TODAY(),-2-1)+1,Applications!I2:I500,"<="&EOMONTH(TODAY(),-2)) | E56: Offer | F56: =COUNTIFS(Applications!J2:J500,"Offer",Applications!B2:B500,"<>")+COUNTIFS(Applications!J2:J500,"Accepted",Applications!B2:B500,"<>")
B57: =TEXT(EOMONTH(TODAY(),-1),"MMM YYYY") | C57: =COUNTIFS(Applications!I2:I500,">="&EOMONTH(TODAY(),-1-1)+1,Applications!I2:I500,"<="&EOMONTH(TODAY(),-1)) | E57: Accepted | F57: =COUNTIFS(Applications!J2:J500,"Accepted",Applications!B2:B500,"<>")
B58: =TEXT(EOMONTH(TODAY(),-0),"MMM YYYY") | C58: =COUNTIFS(Applications!I2:I500,">="&EOMONTH(TODAY(),-0-1)+1,Applications!I2:I500,"<="&EOMONTH(TODAY(),-0))

Sheet Applications
A1: Application ID | B1: Company | C1: Role | D1: Location | E1: Country | F1: Remote | G1: Salary | H1: Source | I1: Date Applied | J1: Status | K1: Priority | L1: Fit Score | M1: Follow-up Date | N1: Recruiter | O1: LinkedIn Recruiter | P1: Interview Date | Q1: Offer | R1: Application URL | S1: Company Career Page | T1: Resume Version | U1: Cover Letter Version | V1: Visa Sponsorship | W1: Employment Type | X1: Work Authorization | Y1: Referral | Z1: Expected Salary | AA1: Current Stage | AB1: Days Since Applied | AC1: Days Until Follow-up | AD1: Interview Count | AE1: Favorite | AF1: Archive | AG1: Notes
A2: ="APP-"&TEXT(ROW()-1,"000") | AB2: =IF(I2="","",TODAY()-I2) | AC2: =IF(M2="","",M2-TODAY()) | AD2: =IF(B2="","",COUNTIFS('Interview Tracker'!A:A,B2))
A3: ="APP-"&TEXT(ROW()-1,"000") | AB3: =IF(I3="","",TODAY()-I3) | AC3: =IF(M3="","",M3-TODAY()) | AD3: =IF(B3="","",COUNTIFS('Interview Tracker'!A:A,B3))
A4: ="APP-"&TEXT(ROW()-1,"000") | AB4: =IF(I4="","",TODAY()-I4) | AC4: =IF(M4="","",M4-TODAY()) | AD4: =IF(B4="","",COUNTIFS('Interview Tracker'!A:A,B4))
A5: ="APP-"&TEXT(ROW()-1,"000") | AB5: =IF(I5="","",TODAY()-I5) | AC5: =IF(M5="","",M5-TODAY()) | AD5: =IF(B5="","",COUNTIFS('Interview Tracker'!A:A,B5))
A6: ="APP-"&TEXT(ROW()-1,"000") | AB6: =IF(I6="","",TODAY()-I6) | AC6: =IF(M6="","",M6-TODAY()) | AD6: =IF(B6="","",COUNTIFS('Interview Tracker'!A:A,B6))
A7: ="APP-"&TEXT(ROW()-1,"000") | AB7: =IF(I7="","",TODAY()-I7) | AC7: =IF(M7="","",M7-TODAY()) | AD7: =IF(B7="","",COUNTIFS('Interview Tracker'!A:A,B7))
A8: ="APP-"&TEXT(ROW()-1,"000") | AB8: =IF(I8="","",TODAY()-I8) | AC8: =IF(M8="","",M8-TODAY()) | AD8: =IF(B8="","",COUNTIFS('Interview Tracker'!A:A,B8))
A9: ="APP-"&TEXT(ROW()-1,"000") | AB9: =IF(I9="","",TODAY()-I9) | AC9: =IF(M9="","",M9-TODAY()) | AD9: =IF(B9="","",COUNTIFS('Interview Tracker'!A:A,B9))
A10: ="APP-"&TEXT(ROW()-1,"000") | AB10: =IF(I10="","",TODAY()-I10) | AC10: =IF(M10="","",M10-TODAY()) | AD10: =IF(B10="","",COUNTIFS('Interview Tracker'!A:A,B10))
A11: ="APP-"&TEXT(ROW()-1,"000") | AB11: =IF(I11="","",TODAY()-I11) | AC11: =IF(M11="","",M11-TODAY()) | AD11: =IF(B11="","",COUNTIFS('Interview Tracker'!A:A,B11))
A12: ="APP-"&TEXT(ROW()-1,"000") | AB12: =IF(I12="","",TODAY()-I12) | AC12: =IF(M12="","",M12-TODAY()) | AD12: =IF(B12="","",COUNTIFS('Interview Tracker'!A:A,B12))
A13: ="APP-"&TEXT(ROW()-1,"000") | AB13: =IF(I13="","",TODAY()-I13) | AC13: =IF(M13="","",M13-TODAY()) | AD13: =IF(B13="","",COUNTIFS('Interview Tracker'!A:A,B13))
... A500: ="APP-"&TEXT(ROW()-1,"000") | AB500: =IF(I500="","",TODAY()-I500) | AC500: =IF(M500="","",M500-TODAY()) | AD500: =IF(B500="","",COUNTIFS('Interview Tracker'!A:A,B500))

Sheet Interview Tracker
A1: Company | B1: Role | C1: Interview Stage | D1: Interviewer | E1: Interview Date | F1: Interview Number | G1: Duration (min) | H1: Preparation Status | I1: Confidence Score | J1: Difficulty | K1: Result | L1: Technical Topics | M1: Coding Questions | N1: Behavioral Questions | O1: Next Step | P1: Notes | Q1: Lessons Learned
A2: Tech Corp | B2: Senior Frontend Developer | C2: Technical | D2: Jane Smith | F2: =IF(A2="","",COUNTIFS($A$2:A2,A2)) | G2: Pending | K2: Pending
F3: =IF(A3="","",COUNTIFS($A$2:A3,A3))
F4: =IF(A4="","",COUNTIFS($A$2:A4,A4))
F5: =IF(A5="","",COUNTIFS($A$2:A5,A5))
F6: =IF(A6="","",COUNTIFS($A$2:A6,A6))
F7: =IF(A7="","",COUNTIFS($A$2:A7,A7))
F8: =IF(A8="","",COUNTIFS($A$2:A8,A8))
F9: =IF(A9="","",COUNTIFS($A$2:A9,A9))
F10: =IF(A10="","",COUNTIFS($A$2:A10,A10))
F11: =IF(A11="","",COUNTIFS($A$2:A11,A11))
F12: =IF(A12="","",COUNTIFS($A$2:A12,A12))
F13: =IF(A13="","",COUNTIFS($A$2:A13,A13))
F14: =IF(A14="","",COUNTIFS($A$2:A14,A14))
... F500: =IF(A500="","",COUNTIFS($A$2:A500,A500))

Sheet Recruiter CRM
A1: Recruiter Name | B1: Company | C1: Email | D1: LinkedIn | E1: Position | F1: Last Contact | G1: Last Reply | H1: Avg Response Time (days) | I1: Next Follow-up | J1: Relationship Status | K1: Company Rating | L1: Priority | M1: Reminder Status | N1: Next Action | O1: Notes
A2: John Doe | B2: Tech Corp | C2: john@techcorp.com | D2: linkedin.com/in/johndoe | E2: Technical Recruiter | H2: 5 | O2: 5

Sheet Target Companies
A1: Company | B1: Industry | C1: Location | D1: Remote | E1: Size | F1: Website | G1: Career Page | H1: Status | I1: Priority | J1: Hiring Status | K1: Visa Sponsor | L1: Remote Friendly | M1: Tech Stack | N1: Glassdoor Rating | O1: LinkedIn Followers | P1: Company Size Category | Q1: Dream Company | R1: Priority Score | S1: Notes
A2: Tech Corp | B2: Software | C2: San Francisco, CA | D2: Yes | E2: 1000+ | F2: techcorp.com | G2: Researching | H2: Researching | I2: High | R2: =IF(A2="","",IF(Q2="Yes",5,0)+IF(I2="Critical",4,IF(I2="High",3,IF(I2="Medium",2,IF(I2="Low",1,0)))))
R3: =IF(A3="","",IF(Q3="Yes",5,0)+IF(I3="Critical",4,IF(I3="High",3,IF(I3="Medium",2,IF(I3="Low",1,0)))))
R4: =IF(A4="","",IF(Q4="Yes",5,0)+IF(I4="Critical",4,IF(I4="High",3,IF(I4="Medium",2,IF(I4="Low",1,0)))))
R5: =IF(A5="","",IF(Q5="Yes",5,0)+IF(I5="Critical",4,IF(I5="High",3,IF(I5="Medium",2,IF(I5="Low",1,0)))))
R6: =IF(A6="","",IF(Q6="Yes",5,0)+IF(I6="Critical",4,IF(I6="High",3,IF(I6="Medium",2,IF(I6="Low",1,0)))))
R7: =IF(A7="","",IF(Q7="Yes",5,0)+IF(I7="Critical",4,IF(I7="High",3,IF(I7="Medium",2,IF(I7="Low",1,0)))))
R8: =IF(A8="","",IF(Q8="Yes",5,0)+IF(I8="Critical",4,IF(I8="High",3,IF(I8="Medium",2,IF(I8="Low",1,0)))))
R9: =IF(A9="","",IF(Q9="Yes",5,0)+IF(I9="Critical",4,IF(I9="High",3,IF(I9="Medium",2,IF(I9="Low",1,0)))))
R10: =IF(A10="","",IF(Q10="Yes",5,0)+IF(I10="Critical",4,IF(I10="High",3,IF(I10="Medium",2,IF(I10="Low",1,0)))))
R11: =IF(A11="","",IF(Q11="Yes",5,0)+IF(I11="Critical",4,IF(I11="High",3,IF(I11="Medium",2,IF(I11="Low",1,0)))))
R12: =IF(A12="","",IF(Q12="Yes",5,0)+IF(I12="Critical",4,IF(I12="High",3,IF(I12="Medium",2,IF(I12="Low",1,0)))))
R13: =IF(A13="","",IF(Q13="Yes",5,0)+IF(I13="Critical",4,IF(I13="High",3,IF(I13="Medium",2,IF(I13="Low",1,0)))))
R14: =IF(A14="","",IF(Q14="Yes",5,0)+IF(I14="Critical",4,IF(I14="High",3,IF(I14="Medium",2,IF(I14="Low",1,0)))))
... R500: =IF(A500="","",IF(Q500="Yes",5,0)+IF(I500="Critical",4,IF(I500="High",3,IF(I500="Medium",2,IF(I500="Low",1,0)))))

Sheet Salary Comparison
A1: Company | B1: Base Salary | C1: Bonus | D1: Equity | E1: Benefits Value | F1: PTO Days | G1: Remote | H1: Visa Sponsorship | I1: Signing Bonus | J1: Relocation Bonus | K1: Annual Compensation | L1: Monthly Income | M1: Hourly Rate | N1: Total Compensation | O1: Estimated Tax (25%) | P1: Net Salary | Q1: Decision Score | R1: Weighted Score | S1: Offer Ranking
A2: Tech Corp | B2: 150000 | C2: 20000 | D2: 50000 | E2: Full Health | F2: 20 days | G2: Yes | H2: Yes | I2: =B2+C2+D2 | K2: =IF(A2="","",B2+C2) | L2: =IF(A2="","",K2/12) | M2: =IF(A2="","",K2/2080) | N2: =IF(A2="","",B2+C2+D2+E2+I2+J2) | O2: =IF(A2="","",N2*0.25) | P2: =IF(A2="","",N2-O2) | Q2: =IF(A2="","",ROUND(B2*0.4+C2*0.1+D2*0.1+E2*0.1+IF(G2="Yes",5000,0)*0.1+F2*500*0.1+IF(H2="Yes",5000,0)*0.1,0)) | R2: =IF(A2="","",ROUND(Q2/1000,1)) | S2: =IF(A2="","",RANK(R2,$R$2:$R$500,0))
K3: =IF(A3="","",B3+C3) | L3: =IF(A3="","",K3/12) | M3: =IF(A3="","",K3/2080) | N3: =IF(A3="","",B3+C3+D3+E3+I3+J3) | O3: =IF(A3="","",N3*0.25) | P3: =IF(A3="","",N3-O3) | Q3: =IF(A3="","",ROUND(B3*0.4+C3*0.1+D3*0.1+E3*0.1+IF(G3="Yes",5000,0)*0.1+F3*500*0.1+IF(H3="Yes",5000,0)*0.1,0)) | R3: =IF(A3="","",ROUND(Q3/1000,1)) | S3: =IF(A3="","",RANK(R3,$R$2:$R$500,0))
K4: =IF(A4="","",B4+C4) | L4: =IF(A4="","",K4/12) | M4: =IF(A4="","",K4/2080) | N4: =IF(A4="","",B4+C4+D4+E4+I4+J4) | O4: =IF(A4="","",N4*0.25) | P4: =IF(A4="","",N4-O4) | Q4: =IF(A4="","",ROUND(B4*0.4+C4*0.1+D4*0.1+E4*0.1+IF(G4="Yes",5000,0)*0.1+F4*500*0.1+IF(H4="Yes",5000,0)*0.1,0)) | R4: =IF(A4="","",ROUND(Q4/1000,1)) | S4: =IF(A4="","",RANK(R4,$R$2:$R$500,0))
K5: =IF(A5="","",B5+C5) | L5: =IF(A5="","",K5/12) | M5: =IF(A5="","",K5/2080) | N5: =IF(A5="","",B5+C5+D5+E5+I5+J5) | O5: =IF(A5="","",N5*0.25) | P5: =IF(A5="","",N5-O5) | Q5: =IF(A5="","",ROUND(B5*0.4+C5*0.1+D5*0.1+E5*0.1+IF(G5="Yes",5000,0)*0.1+F5*500*0.1+IF(H5="Yes",5000,0)*0.1,0)) | R5: =IF(A5="","",ROUND(Q5/1000,1)) | S5: =IF(A5="","",RANK(R5,$R$2:$R$500,0))
K6: =IF(A6="","",B6+C6) | L6: =IF(A6="","",K6/12) | M6: =IF(A6="","",K6/2080) | N6: =IF(A6="","",B6+C6+D6+E6+I6+J6) | O6: =IF(A6="","",N6*0.25) | P6: =IF(A6="","",N6-O6) | Q6: =IF(A6="","",ROUND(B6*0.4+C6*0.1+D6*0.1+E6*0.1+IF(G6="Yes",5000,0)*0.1+F6*500*0.1+IF(H6="Yes",5000,0)*0.1,0)) | R6: =IF(A6="","",ROUND(Q6/1000,1)) | S6: =IF(A6="","",RANK(R6,$R$2:$R$500,0))
K7: =IF(A7="","",B7+C7) | L7: =IF(A7="","",K7/12) | M7: =IF(A7="","",K7/2080) | N7: =IF(A7="","",B7+C7+D7+E7+I7+J7) | O7: =IF(A7="","",N7*0.25) | P7: =IF(A7="","",N7-O7) | Q7: =IF(A7="","",ROUND(B7*0.4+C7*0.1+D7*0.1+E7*0.1+IF(G7="Yes",5000,0)*0.1+F7*500*0.1+IF(H7="Yes",5000,0)*0.1,0)) | R7: =IF(A7="","",ROUND(Q7/1000,1)) | S7: =IF(A7="","",RANK(R7,$R$2:$R$500,0))
K8: =IF(A8="","",B8+C8) | L8: =IF(A8="","",K8/12) | M8: =IF(A8="","",K8/2080) | N8: =IF(A8="","",B8+C8+D8+E8+I8+J8) | O8: =IF(A8="","",N8*0.25) | P8: =IF(A8="","",N8-O8) | Q8: =IF(A8="","",ROUND(B8*0.4+C8*0.1+D8*0.1+E8*0.1+IF(G8="Yes",5000,0)*0.1+F8*500*0.1+IF(H8="Yes",5000,0)*0.1,0)) | R8: =IF(A8="","",ROUND(Q8/1000,1)) | S8: =IF(A8="","",RANK(R8,$R$2:$R$500,0))
K9: =IF(A9="","",B9+C9) | L9: =IF(A9="","",K9/12) | M9: =IF(A9="","",K9/2080) | N9: =IF(A9="","",B9+C9+D9+E9+I9+J9) | O9: =IF(A9="","",N9*0.25) | P9: =IF(A9="","",N9-O9) | Q9: =IF(A9="","",ROUND(B9*0.4+C9*0.1+D9*0.1+E9*0.1+IF(G9="Yes",5000,0)*0.1+F9*500*0.1+IF(H9="Yes",5000,0)*0.1,0)) | R9: =IF(A9="","",ROUND(Q9/1000,1)) | S9: =IF(A9="","",RANK(R9,$R$2:$R$500,0))
K10: =IF(A10="","",B10+C10) | L10: =IF(A10="","",K10/12) | M10: =IF(A10="","",K10/2080) | N10: =IF(A10="","",B10+C10+D10+E10+I10+J10) | O10: =IF(A10="","",N10*0.25) | P10: =IF(A10="","",N10-O10) | Q10: =IF(A10="","",ROUND(B10*0.4+C10*0.1+D10*0.1+E10*0.1+IF(G10="Yes",5000,0)*0.1+F10*500*0.1+IF(H10="Yes",5000,0)*0.1,0)) | R10: =IF(A10="","",ROUND(Q10/1000,1)) | S10: =IF(A10="","",RANK(R10,$R$2:$R$500,0))
K11: =IF(A11="","",B11+C11) | L11: =IF(A11="","",K11/12) | M11: =IF(A11="","",K11/2080) | N11: =IF(A11="","",B11+C11+D11+E11+I11+J11) | O11: =IF(A11="","",N11*0.25) | P11: =IF(A11="","",N11-O11) | Q11: =IF(A11="","",ROUND(B11*0.4+C11*0.1+D11*0.1+E11*0.1+IF(G11="Yes",5000,0)*0.1+F11*500*0.1+IF(H11="Yes",5000,0)*0.1,0)) | R11: =IF(A11="","",ROUND(Q11/1000,1)) | S11: =IF(A11="","",RANK(R11,$R$2:$R$500,0))
K12: =IF(A12="","",B12+C12) | L12: =IF(A12="","",K12/12) | M12: =IF(A12="","",K12/2080) | N12: =IF(A12="","",B12+C12+D12+E12+I12+J12) | O12: =IF(A12="","",N12*0.25) | P12: =IF(A12="","",N12-O12) | Q12: =IF(A12="","",ROUND(B12*0.4+C12*0.1+D12*0.1+E12*0.1+IF(G12="Yes",5000,0)*0.1+F12*500*0.1+IF(H12="Yes",5000,0)*0.1,0)) | R12: =IF(A12="","",ROUND(Q12/1000,1)) | S12: =IF(A12="","",RANK(R12,$R$2:$R$500,0))
K13: =IF(A13="","",B13+C13) | L13: =IF(A13="","",K13/12) | M13: =IF(A13="","",K13/2080) | N13: =IF(A13="","",B13+C13+D13+E13+I13+J13) | O13: =IF(A13="","",N13*0.25) | P13: =IF(A13="","",N13-O13) | Q13: =IF(A13="","",ROUND(B13*0.4+C13*0.1+D13*0.1+E13*0.1+IF(G13="Yes",5000,0)*0.1+F13*500*0.1+IF(H13="Yes",5000,0)*0.1,0)) | R13: =IF(A13="","",ROUND(Q13/1000,1)) | S13: =IF(A13="","",RANK(R13,$R$2:$R$500,0))
K14: =IF(A14="","",B14+C14) | L14: =IF(A14="","",K14/12) | M14: =IF(A14="","",K14/2080) | N14: =IF(A14="","",B14+C14+D14+E14+I14+J14) | O14: =IF(A14="","",N14*0.25) | P14: =IF(A14="","",N14-O14) | Q14: =IF(A14="","",ROUND(B14*0.4+C14*0.1+D14*0.1+E14*0.1+IF(G14="Yes",5000,0)*0.1+F14*500*0.1+IF(H14="Yes",5000,0)*0.1,0)) | R14: =IF(A14="","",ROUND(Q14/1000,1)) | S14: =IF(A14="","",RANK(R14,$R$2:$R$500,0))
... K500: =IF(A500="","",B500+C500) | L500: =IF(A500="","",K500/12) | M500: =IF(A500="","",K500/2080) | N500: =IF(A500="","",B500+C500+D500+E500+I500+J500) | O500: =IF(A500="","",N500*0.25) | P500: =IF(A500="","",N500-O500) | Q500: =IF(A500="","",ROUND(B500*0.4+C500*0.1+D500*0.1+E500*0.1+IF(G500="Yes",5000,0)*0.1+F500*500*0.1+IF(H500="Yes",5000,0)*0.1,0)) | R500: =IF(A500="","",ROUND(Q500/1000,1)) | S500: =IF(A500="","",RANK(R500,$R$2:$R$500,0))

Sheet Weekly Planner
A1: Week Of | B1: Applications Goal | C1: Completed | D1: Networking | E1: Interview Prep | F1: Learning | G1: Follow-ups | H1: Reflection
A2: 2026-06-29 | B2: 20 | C2: 0 | D2: 3 coffee chats | E2: 2 companies | F2: React patterns | G2: 5 follow-ups

Sheet Statistics
B2: Job Search Statistics & Analytics
B3: Automatically calculated from your Applications data
B6: Application Metrics | E6: Conversion Rates
B7: Applications Submitted | C7: =COUNTA(Applications!B2:B500) | E7: Response Rate | F7: =IFERROR(ROUND((COUNTA(Applications!B2:B500)-COUNTIFS(Applications!J2:J500,"Applied",Applications!B2:B500,"<>")-COUNTIFS(Applications!J2:J500,"Ghosted",Applications!B2:B500,"<>"))/COUNTA(Applications!B2:B500),2),0)
B8: Applications per Week | C8: =IFERROR(ROUND(COUNTA(Applications!B2:B500)/MAX(1,ROUND((TODAY()-MIN(Applications!I2:I500))/7,0)),1),0) | E8: Interview Rate | F8: =IFERROR(ROUND(COUNTIFS(Applications!J2:J500,"*Interview*",Applications!B2:B500,"<>")/COUNTA(Applications!B2:B500),2),0)
B9: Applications per Month | C9: =IFERROR(ROUND(COUNTA(Applications!B2:B500)/MAX(1,ROUND((TODAY()-MIN(Applications!I2:I500))/30,0)),1),0) | E9: Offer Rate | F9: =IFERROR(ROUND((COUNTIFS(Applications!J2:J500,"Offer",Applications!B2:B500,"<>")+COUNTIFS(Applications!J2:J500,"Accepted",Applications!B2:B500,"<>"))/COUNTA(Applications!B2:B500),2),0)
B10: Avg Time Until Response (days) | C10: =IFERROR(ROUND(AVERAGEIFS(Applications!I2:I500,Applications!J2:J500,"<>Applied",Applications!J2:J500,"<>")-MIN(Applications!I2:I500),0),0) | E10: Acceptance Rate | F10: =IFERROR(ROUND(COUNTIFS(Applications!J2:J500,"Accepted",Applications!B2:B500,"<>")/(COUNTIFS(Applications!J2:J500,"Offer",Applications!B2:B500,"<>")+COUNTIFS(Applications!J2:J500,"Accepted",Applications!B2:B500,"<>")),2),0)
B11: Avg Time Until Interview (days) | C11: =IFERROR(ROUND(AVERAGEIFS(Applications!I2:I500,Applications!J2:J500,"*Interview*")-AVERAGEIFS(Applications!I2:I500,Applications!J2:J500,"*Interview*"),0),0) | E11: Ghost Rate | F11: =IFERROR(ROUND(COUNTIFS(Applications!J2:J500,"Ghosted",Applications!B2:B500,"<>")/COUNTA(Applications!B2:B500),2),0)
B12: Avg Time Until Offer (days) | C12: =IFERROR(ROUND(AVERAGEIFS(Applications!I2:I500,Applications!J2:J500,"Offer")-AVERAGEIFS(Applications!I2:I500,Applications!J2:J500,"Offer"),0),0) | E12: Rejection Rate | F12: =IFERROR(ROUND(COUNTIFS(Applications!J2:J500,"Rejected",Applications!B2:B500,"<>")/COUNTA(Applications!B2:B500),2),0)
B14: Salary Analytics | E14: Top Insights
B15: Highest Salary | C15: =IFERROR(MAX(Applications!G2:G500),0) | E15: Most Common Job Title | F15: =IFERROR(INDEX(Applications!C2:C500,MODE.MATCH(Applications!C2:C500)),0)
B16: Lowest Salary | C16: =IFERROR(MINIFS(Applications!G2:G500,Applications!G2:G500,">0"),0) | E16: Most Common Location | F16: =IFERROR(INDEX(Applications!D2:D500,MODE.MATCH(Applications!D2:D500)),0)
B17: Average Salary | C17: =IFERROR(AVERAGEIF(Applications!G2:G500,">0"),0) | E17: Most Successful Source | F17: =IFERROR(INDEX(Applications!H2:H500,MATCH(MAX(COUNTIFS(Applications!H2:H500,Applications!H2:H500,Applications!J2:J500,"Offer")+COUNTIFS(Applications!H2:H500,Applications!H2:H500,Applications!J2:J500,"Accepted")),COUNTIFS(Applications!H2:H500,Applications!H2:H500,Applications!J2:J500,"Offer")+COUNTIFS(Applications!H2:H500,Applications!H2:H500,Applications!J2:J500,"Accepted"),0)),0)
B18: Median Salary | C18: =IFERROR(MEDIAN(IF(Applications!G2:G500>0,Applications!G2:G500)),0) | E18: Most Applied Company | F18: =IFERROR(INDEX(Applications!B2:B500,MATCH(MAX(COUNTIF(Applications!B2:B500,Applications!B2:B500)),COUNTIF(Applications!B2:B500,Applications!B2:B500),0)),0)
B19: Avg Fit Score | C19: =IFERROR(ROUND(AVERAGEIF(Applications!L2:L500,">0"),1),0) | E19: Total Companies | F19: =IFERROR(SUMPRODUCT(1/COUNTIF(Applications!B2:B500,Applications!B2:B500&"")),0)
B20: Avg Decision Score | C20: =IFERROR(ROUND(AVERAGE('Offer Decision Matrix'!R2:R500),1),0) | E20: Avg Days Active | F20: =IFERROR(ROUND(AVERAGE(Applications!AB2:AB500),0),0)

Sheet Notes
B2: Notes
B4: General Notes

Sheet Portfolio Projects
A1: Project Name | B1: Description | C1: Status | D1: Start Date | E1: Completion Date | F1: Type | G1: Tech Stack | H1: GitHub URL | I1: Live Demo | J1: Skills Demonstrated | K1: Complexity | L1: Time Investment | M1: Showcase Ready | N1: Interview Worthy | O1: Notes
A2: E-Commerce Platform | B2: Full-stack e-commerce solution | C2: Completed | D2: 2026-01-15 | E2: 2026-03-30 | F2: Web App | G2: React, Node.js, MongoDB, Stripe | H2: github.com/user/ecommerce | I2: demo.example.com | J2: Frontend, Backend, Database, API | K2: Advanced | L2: 120 hours | M2: Ready | N2: Yes

Sheet Networking Tracker
A1: Contact Name | B1: Company | C1: LinkedIn | D1: Email | E1: Connection Date | F1: Connection Type | G1: Platform | H1: Relationship Type | I1: Last Contact | J1: Next Follow-up | K1: Follow-up Status | L1: Meeting Scheduled | M1: Coffee Chat | N1: Referral Requested | O1: Referral Received | P1: Priority | Q1: Network Score | R1: Relationship Score | S1: Notes
A2: Jane Smith | B2: Google | C2: linkedin.com/in/janesmith | D2: jane@google.com | E2: 2026-06-29 | F2: LinkedIn Connection | H2: LinkedIn Connection | I2: 8 | J2: Not Asked | L2: No | M2: No | Q2: 8 | S2: No

Sheet Skill Gap Analysis
A1: Skill Category | B1: Skill Name | C1: Current Level | D1: Target Level | E1: Gap | F1: Gap Level | G1: Learning Resource | H1: Priority | I1: Status | J1: Difficulty | K1: Start Date | L1: Target Date | M1: Estimated Hours | N1: Hours Invested | O1: Estimated Completion | P1: Progress % | Q1: Progress Bar | R1: Notes
A2: Frontend | B2: React | C2: Intermediate | D2: Advanced | E2: 1 level | F2: =IF(C2="","",IF(D2="","",IF(C2="Beginner",1,IF(C2="Intermediate",2,IF(C2="Advanced",3,4)))-IF(D2="Beginner",1,IF(D2="Intermediate",2,IF(D2="Advanced",3,4))))) | G2: React Official Docs | H2: High | I2: Not Started | K2: 0% | L2: 0 | P2: =IF(N2="","",IF(M2=0,0,MIN(N2/M2,1))) | Q2: =IF(P2="","",REPT("█",ROUND(P2*20,0))&REPT("░",20-ROUND(P2*20,0)))
F3: =IF(C3="","",IF(D3="","",IF(C3="Beginner",1,IF(C3="Intermediate",2,IF(C3="Advanced",3,4)))-IF(D3="Beginner",1,IF(D3="Intermediate",2,IF(D3="Advanced",3,4))))) | P3: =IF(N3="","",IF(M3=0,0,MIN(N3/M3,1))) | Q3: =IF(P3="","",REPT("█",ROUND(P3*20,0))&REPT("░",20-ROUND(P3*20,0)))
F4: =IF(C4="","",IF(D4="","",IF(C4="Beginner",1,IF(C4="Intermediate",2,IF(C4="Advanced",3,4)))-IF(D4="Beginner",1,IF(D4="Intermediate",2,IF(D4="Advanced",3,4))))) | P4: =IF(N4="","",IF(M4=0,0,MIN(N4/M4,1))) | Q4: =IF(P4="","",REPT("█",ROUND(P4*20,0))&REPT("░",20-ROUND(P4*20,0)))
F5: =IF(C5="","",IF(D5="","",IF(C5="Beginner",1,IF(C5="Intermediate",2,IF(C5="Advanced",3,4)))-IF(D5="Beginner",1,IF(D5="Intermediate",2,IF(D5="Advanced",3,4))))) | P5: =IF(N5="","",IF(M5=0,0,MIN(N5/M5,1))) | Q5: =IF(P5="","",REPT("█",ROUND(P5*20,0))&REPT("░",20-ROUND(P5*20,0)))
F6: =IF(C6="","",IF(D6="","",IF(C6="Beginner",1,IF(C6="Intermediate",2,IF(C6="Advanced",3,4)))-IF(D6="Beginner",1,IF(D6="Intermediate",2,IF(D6="Advanced",3,4))))) | P6: =IF(N6="","",IF(M6=0,0,MIN(N6/M6,1))) | Q6: =IF(P6="","",REPT("█",ROUND(P6*20,0))&REPT("░",20-ROUND(P6*20,0)))
F7: =IF(C7="","",IF(D7="","",IF(C7="Beginner",1,IF(C7="Intermediate",2,IF(C7="Advanced",3,4)))-IF(D7="Beginner",1,IF(D7="Intermediate",2,IF(D7="Advanced",3,4))))) | P7: =IF(N7="","",IF(M7=0,0,MIN(N7/M7,1))) | Q7: =IF(P7="","",REPT("█",ROUND(P7*20,0))&REPT("░",20-ROUND(P7*20,0)))
F8: =IF(C8="","",IF(D8="","",IF(C8="Beginner",1,IF(C8="Intermediate",2,IF(C8="Advanced",3,4)))-IF(D8="Beginner",1,IF(D8="Intermediate",2,IF(D8="Advanced",3,4))))) | P8: =IF(N8="","",IF(M8=0,0,MIN(N8/M8,1))) | Q8: =IF(P8="","",REPT("█",ROUND(P8*20,0))&REPT("░",20-ROUND(P8*20,0)))
F9: =IF(C9="","",IF(D9="","",IF(C9="Beginner",1,IF(C9="Intermediate",2,IF(C9="Advanced",3,4)))-IF(D9="Beginner",1,IF(D9="Intermediate",2,IF(D9="Advanced",3,4))))) | P9: =IF(N9="","",IF(M9=0,0,MIN(N9/M9,1))) | Q9: =IF(P9="","",REPT("█",ROUND(P9*20,0))&REPT("░",20-ROUND(P9*20,0)))
F10: =IF(C10="","",IF(D10="","",IF(C10="Beginner",1,IF(C10="Intermediate",2,IF(C10="Advanced",3,4)))-IF(D10="Beginner",1,IF(D10="Intermediate",2,IF(D10="Advanced",3,4))))) | P10: =IF(N10="","",IF(M10=0,0,MIN(N10/M10,1))) | Q10: =IF(P10="","",REPT("█",ROUND(P10*20,0))&REPT("░",20-ROUND(P10*20,0)))
F11: =IF(C11="","",IF(D11="","",IF(C11="Beginner",1,IF(C11="Intermediate",2,IF(C11="Advanced",3,4)))-IF(D11="Beginner",1,IF(D11="Intermediate",2,IF(D11="Advanced",3,4))))) | P11: =IF(N11="","",IF(M11=0,0,MIN(N11/M11,1))) | Q11: =IF(P11="","",REPT("█",ROUND(P11*20,0))&REPT("░",20-ROUND(P11*20,0)))
F12: =IF(C12="","",IF(D12="","",IF(C12="Beginner",1,IF(C12="Intermediate",2,IF(C12="Advanced",3,4)))-IF(D12="Beginner",1,IF(D12="Intermediate",2,IF(D12="Advanced",3,4))))) | P12: =IF(N12="","",IF(M12=0,0,MIN(N12/M12,1))) | Q12: =IF(P12="","",REPT("█",ROUND(P12*20,0))&REPT("░",20-ROUND(P12*20,0)))
F13: =IF(C13="","",IF(D13="","",IF(C13="Beginner",1,IF(C13="Intermediate",2,IF(C13="Advanced",3,4)))-IF(D13="Beginner",1,IF(D13="Intermediate",2,IF(D13="Advanced",3,4))))) | P13: =IF(N13="","",IF(M13=0,0,MIN(N13/M13,1))) | Q13: =IF(P13="","",REPT("█",ROUND(P13*20,0))&REPT("░",20-ROUND(P13*20,0)))
F14: =IF(C14="","",IF(D14="","",IF(C14="Beginner",1,IF(C14="Intermediate",2,IF(C14="Advanced",3,4)))-IF(D14="Beginner",1,IF(D14="Intermediate",2,IF(D14="Advanced",3,4))))) | P14: =IF(N14="","",IF(M14=0,0,MIN(N14/M14,1))) | Q14: =IF(P14="","",REPT("█",ROUND(P14*20,0))&REPT("░",20-ROUND(P14*20,0)))
... F500: =IF(C500="","",IF(D500="","",IF(C500="Beginner",1,IF(C500="Intermediate",2,IF(C500="Advanced",3,4)))-IF(D500="Beginner",1,IF(D500="Intermediate",2,IF(D500="Advanced",3,4))))) | P500: =IF(N500="","",IF(M500=0,0,MIN(N500/M500,1))) | Q500: =IF(P500="","",REPT("█",ROUND(P500*20,0))&REPT("░",20-ROUND(P500*20,0)))

Sheet Cover Letter Tracker
A1: Company | B1: Role | C1: Version | D1: Date Created | E1: Date Sent | F1: Template Used | G1: Customization Level | H1: Response Received | I1: Interview Scheduled | J1: Success Rate | K1: A/B Test Group | L1: Notes
A2: Tech Corp | B2: Senior Frontend Developer | C2: v1.0 | D2: 2026-06-29 | F2: Template A | G2: Heavy Customization | H2: No | I2: No | J2: 0% | K2: A

Sheet Job Search Calendar
A1: Date | B1: Event Type | C1: Company | D1: Role | E1: Time | F1: Location/Link | G1: Preparation Needed | H1: Status | I1: Priority | J1: Follow-up Required | K1: Notes
A2: 2026-06-29 | B2: Technical Assessment | C2: Tech Corp | D2: Senior Frontend Developer | E2: 2:00 PM | F2: Online (Zoom) | G2: Practice coding problems | H2: Scheduled | I2: High | J2: Yes

Sheet Learning Resources
A1: Resource Name | B1: Type | C1: Provider | D1: Topic | E1: URL | F1: Cost | G1: Duration | H1: Start Date | I1: Completion Date | J1: Progress % | K1: Certificate | L1: Priority | M1: Rating | N1: Notes
A2: React - The Complete Guide | B2: Course | C2: Udemy | D2: React | E2: udemy.com/course/react | F2: $15 | G2: 40 hours | J2: 0% | K2: Yes | L2: High

Sheet Offer Decision Matrix
A1: Company | B1: Base Salary | C1: Bonus | D1: Equity | E1: Benefits Value | F1: Remote Flexibility | G1: Visa Sponsorship | H1: Career Growth | I1: Manager Quality | J1: Engineering Culture | K1: Tech Stack | L1: Learning Potential | M1: Work-Life Balance | N1: Location | O1: Promotion Opportunities | P1: Company Stability | Q1: PTO Days | R1: Weighted Score | S1: Rank | T1: Decision
A2: Tech Corp | B2: 150000 | C2: 20000 | D2: 50000 | E2: 15000 | F2: Yes | G2: 20 | H2: 9 | I2: 8 | J2: 9 | K2: 9 | L2: 9 | M2: 8 | N2: San Francisco | O2: 30 min | P2: Yes | Q2: 8 | R2: =IF(A2="","",ROUND(B2/10000*0.25+C2/10000*0.05+D2/10000*0.05+E2/10000*0.05+IF(F2="Yes",10,IF(F2="No",0,5))*0.10+IF(G2="Yes",10,IF(G2="No",0,5))*0.05+H2*0.10+I2*0.10+J2*0.05+K2*0.05+L2*0.05+M2*0.05+N2*0.03+O2*0.02+P2*0.05,1)) | S2: =IF(A2="","",RANK(R2,$R$2:$R$500,0)) | T2: Pending
R3: =IF(A3="","",ROUND(B3/10000*0.25+C3/10000*0.05+D3/10000*0.05+E3/10000*0.05+IF(F3="Yes",10,IF(F3="No",0,5))*0.10+IF(G3="Yes",10,IF(G3="No",0,5))*0.05+H3*0.10+I3*0.10+J3*0.05+K3*0.05+L3*0.05+M3*0.05+N3*0.03+O3*0.02+P3*0.05,1)) | S3: =IF(A3="","",RANK(R3,$R$2:$R$500,0))
R4: =IF(A4="","",ROUND(B4/10000*0.25+C4/10000*0.05+D4/10000*0.05+E4/10000*0.05+IF(F4="Yes",10,IF(F4="No",0,5))*0.10+IF(G4="Yes",10,IF(G4="No",0,5))*0.05+H4*0.10+I4*0.10+J4*0.05+K4*0.05+L4*0.05+M4*0.05+N4*0.03+O4*0.02+P4*0.05,1)) | S4: =IF(A4="","",RANK(R4,$R$2:$R$500,0))
R5: =IF(A5="","",ROUND(B5/10000*0.25+C5/10000*0.05+D5/10000*0.05+E5/10000*0.05+IF(F5="Yes",10,IF(F5="No",0,5))*0.10+IF(G5="Yes",10,IF(G5="No",0,5))*0.05+H5*0.10+I5*0.10+J5*0.05+K5*0.05+L5*0.05+M5*0.05+N5*0.03+O5*0.02+P5*0.05,1)) | S5: =IF(A5="","",RANK(R5,$R$2:$R$500,0))
R6: =IF(A6="","",ROUND(B6/10000*0.25+C6/10000*0.05+D6/10000*0.05+E6/10000*0.05+IF(F6="Yes",10,IF(F6="No",0,5))*0.10+IF(G6="Yes",10,IF(G6="No",0,5))*0.05+H6*0.10+I6*0.10+J6*0.05+K6*0.05+L6*0.05+M6*0.05+N6*0.03+O6*0.02+P6*0.05,1)) | S6: =IF(A6="","",RANK(R6,$R$2:$R$500,0))
R7: =IF(A7="","",ROUND(B7/10000*0.25+C7/10000*0.05+D7/10000*0.05+E7/10000*0.05+IF(F7="Yes",10,IF(F7="No",0,5))*0.10+IF(G7="Yes",10,IF(G7="No",0,5))*0.05+H7*0.10+I7*0.10+J7*0.05+K7*0.05+L7*0.05+M7*0.05+N7*0.03+O7*0.02+P7*0.05,1)) | S7: =IF(A7="","",RANK(R7,$R$2:$R$500,0))
R8: =IF(A8="","",ROUND(B8/10000*0.25+C8/10000*0.05+D8/10000*0.05+E8/10000*0.05+IF(F8="Yes",10,IF(F8="No",0,5))*0.10+IF(G8="Yes",10,IF(G8="No",0,5))*0.05+H8*0.10+I8*0.10+J8*0.05+K8*0.05+L8*0.05+M8*0.05+N8*0.03+O8*0.02+P8*0.05,1)) | S8: =IF(A8="","",RANK(R8,$R$2:$R$500,0))
R9: =IF(A9="","",ROUND(B9/10000*0.25+C9/10000*0.05+D9/10000*0.05+E9/10000*0.05+IF(F9="Yes",10,IF(F9="No",0,5))*0.10+IF(G9="Yes",10,IF(G9="No",0,5))*0.05+H9*0.10+I9*0.10+J9*0.05+K9*0.05+L9*0.05+M9*0.05+N9*0.03+O9*0.02+P9*0.05,1)) | S9: =IF(A9="","",RANK(R9,$R$2:$R$500,0))
R10: =IF(A10="","",ROUND(B10/10000*0.25+C10/10000*0.05+D10/10000*0.05+E10/10000*0.05+IF(F10="Yes",10,IF(F10="No",0,5))*0.10+IF(G10="Yes",10,IF(G10="No",0,5))*0.05+H10*0.10+I10*0.10+J10*0.05+K10*0.05+L10*0.05+M10*0.05+N10*0.03+O10*0.02+P10*0.05,1)) | S10: =IF(A10="","",RANK(R10,$R$2:$R$500,0))
R11: =IF(A11="","",ROUND(B11/10000*0.25+C11/10000*0.05+D11/10000*0.05+E11/10000*0.05+IF(F11="Yes",10,IF(F11="No",0,5))*0.10+IF(G11="Yes",10,IF(G11="No",0,5))*0.05+H11*0.10+I11*0.10+J11*0.05+K11*0.05+L11*0.05+M11*0.05+N11*0.03+O11*0.02+P11*0.05,1)) | S11: =IF(A11="","",RANK(R11,$R$2:$R$500,0))
R12: =IF(A12="","",ROUND(B12/10000*0.25+C12/10000*0.05+D12/10000*0.05+E12/10000*0.05+IF(F12="Yes",10,IF(F12="No",0,5))*0.10+IF(G12="Yes",10,IF(G12="No",0,5))*0.05+H12*0.10+I12*0.10+J12*0.05+K12*0.05+L12*0.05+M12*0.05+N12*0.03+O12*0.02+P12*0.05,1)) | S12: =IF(A12="","",RANK(R12,$R$2:$R$500,0))
R13: =IF(A13="","",ROUND(B13/10000*0.25+C13/10000*0.05+D13/10000*0.05+E13/10000*0.05+IF(F13="Yes",10,IF(F13="No",0,5))*0.10+IF(G13="Yes",10,IF(G13="No",0,5))*0.05+H13*0.10+I13*0.10+J13*0.05+K13*0.05+L13*0.05+M13*0.05+N13*0.03+O13*0.02+P13*0.05,1)) | S13: =IF(A13="","",RANK(R13,$R$2:$R$500,0))
R14: =IF(A14="","",ROUND(B14/10000*0.25+C14/10000*0.05+D14/10000*0.05+E14/10000*0.05+IF(F14="Yes",10,IF(F14="No",0,5))*0.10+IF(G14="Yes",10,IF(G14="No",0,5))*0.05+H14*0.10+I14*0.10+J14*0.05+K14*0.05+L14*0.05+M14*0.05+N14*0.03+O14*0.02+P14*0.05,1)) | S14: =IF(A14="","",RANK(R14,$R$2:$R$500,0))
... R500: =IF(A500="","",ROUND(B500/10000*0.25+C500/10000*0.05+D500/10000*0.05+E500/10000*0.05+IF(F500="Yes",10,IF(F500="No",0,5))*0.10+IF(G500="Yes",10,IF(G500="No",0,5))*0.05+H500*0.10+I500*0.10+J500*0.05+K500*0.05+L500*0.05+M500*0.05+N500*0.03+O500*0.02+P500*0.05,1)) | S500: =IF(A500="","",RANK(R500,$R$2:$R$500,0))
